README.md
setup.py
DevDoc.egg-info/PKG-INFO
DevDoc.egg-info/SOURCES.txt
DevDoc.egg-info/dependency_links.txt
DevDoc.egg-info/entry_points.txt
DevDoc.egg-info/requires.txt
DevDoc.egg-info/top_level.txt
devdoc/__init__.py
devdoc/devdoc.py
devdoc/main.py